{"commitInfo":{"timestamp":1741027596172,"operation":"WRITE","operationParameters":{"mode":"Append","partitionBy":"[]"},"readVersion":0,"isolationLevel":"Serializable","isBlindAppend":true,"operationMetrics":{"numFiles":"2","numOutputRows":"2","numOutputBytes":"904"},"engineInfo":"Apache-Spark/3.5.3 Delta-Lake/3.4.0-SNAPSHOT","txnId":"b687ed24-db96-4f7d-b9c1-c68a3aa97d62"}}
{"add":{"path":"part-00000-c2b37c89-e93e-48a9-a42f-654388c2220d-c000.snappy.parquet","partitionValues":{},"size":452,"modificationTime":1741027596165,"dataChange":true,"stats":"{\"numRecords\":1,\"minValues\":{\"id\":4},\"maxValues\":{\"id\":4},\"nullCount\":{\"id\":0}}"}}
{"add":{"path":"part-00001-0790dd25-9456-412d-a770-4e4b13b5685d-c000.snappy.parquet","partitionValues":{},"size":452,"modificationTime":1741027596170,"dataChange":true,"stats":"{\"numRecords\":1,\"minValues\":{\"id\":5},\"maxValues\":{\"id\":5},\"nullCount\":{\"id\":0}}"}}
